happyfeat/__init__.py
happyfeat/bcipipeline_setup.py
happyfeat/featureExtractionInterface.py
happyfeat/happyfeat_welcome.py
happyfeat/lib/Spectral_Analysis.py
happyfeat/lib/Statistical_analysis.py
happyfeat/lib/Visualization_Data.py
happyfeat/lib/__init__.py
happyfeat/lib/bcipipeline_settings.py
happyfeat/lib/extractMetaData.py
happyfeat/lib/featureExtractUtils.py
happyfeat/lib/mergeRuns.py
happyfeat/lib/mergeRunsCsv.py
happyfeat/lib/modifyOpenvibeScen.py
happyfeat/lib/myProgressBar.py
happyfeat/lib/utils.py
happyfeat/lib/workThreads.py
happyfeat/lib/workspaceMgmt.py
happyfeat/templates-connectivity/__init__.py
happyfeat/templates-connectivity/concat-runs.xml
happyfeat/templates-connectivity/mi-stimulations.lua
happyfeat/templates-connectivity/sc1-monitor-acq.xml
happyfeat/templates-connectivity/sc2-extract.xml
happyfeat/templates-connectivity/sc2-train-composite.xml
happyfeat/templates-connectivity/sc2-train-speedup-finalize.xml
happyfeat/templates-connectivity/sc2-train-speedup-firststep.xml
happyfeat/templates-connectivity/sc3-online.xml
happyfeat/templates-connectivity/sc4-run-replay.xml
happyfeat/templates-mixed/__init__.py
happyfeat/templates-mixed/concat-runs.xml
happyfeat/templates-mixed/mi-stimulations.lua
happyfeat/templates-mixed/sc1-monitor-acq.xml
happyfeat/templates-mixed/sc2-extract.xml
happyfeat/templates-mixed/sc2-train-composite.xml
happyfeat/templates-mixed/sc2-train-speedup-finalize.xml
happyfeat/templates-mixed/sc2-train-speedup-firststep.xml
happyfeat/templates-mixed/sc3-online.xml
happyfeat/templates-mixed/sc4-run-replay.xml
happyfeat/templates-mixed-bcinet/__init__.py
happyfeat/templates-mixed-bcinet/concat-runs.xml
happyfeat/templates-mixed-bcinet/mi-stimulations.lua
happyfeat/templates-mixed-bcinet/sc1-monitor-acq.xml
happyfeat/templates-mixed-bcinet/sc2-extract.xml
happyfeat/templates-mixed-bcinet/sc2-train-composite.xml
happyfeat/templates-mixed-bcinet/sc2-train-speedup-finalize.xml
happyfeat-0.3.0.dist-info/METADATA
happyfeat-0.3.0.dist-info/WHEEL
happyfeat-0.3.0.dist-info/entry_points.txt
happyfeat-0.3.0.dist-info/licenses/LICENSE.md
happyfeat-0.3.0.dist-info/RECORD
