Metadata-Version: 2.4
Name: happyfeat
Version: 0.3.0
Summary: Package for HappyFeat
Project-URL: Homepage, https://github.com/Inria-NERV/happyFeat
Author-email: Inria NERV <adesbois@inria.fr>
License-File: LICENSE.md
Classifier: License :: OSI Approved :: BSD License
Classifier: Operating System :: Microsoft :: Windows
Classifier: Operating System :: POSIX :: Linux
Classifier: Programming Language :: Python :: 3
Requires-Python: ==3.12.8
Requires-Dist: matplotlib==3.8.4
Requires-Dist: mne==1.9.0
Requires-Dist: numpy==1.26.4
Requires-Dist: pandas==2.2.1
Requires-Dist: plotly==5.24.1
Requires-Dist: pyside6==6.8.1
Requires-Dist: ruamel-yaml==0.18.6
Requires-Dist: scipy>=1.7.1
Requires-Dist: shutils>=0.1.0
Requires-Dist: spectrum>=0.8.0
Requires-Dist: statsmodels>=0.13.1
